[
  {
    "id": "EOL6Id55wq8",
    "title": "Death Of Me - மிரளவைக்கும் திகில் திரைப்படம் | Super Hit Cinema | Thanthi One | 11th January",
    "description": "A vacationing couple on a Thai island wakes up with no memory of the previous night, only to find a video showing one of them killing the other. As they unravel the mystery, they face a web of black magic, murder, and betrayal, questioning if the woman is guilty of avoiding a sacrifice or if something more sinister, like Mother Nature, is at play.\nTo Watch Super Hit Cinemas : \nDon't forget to SUBSCRIBE Thanthi One YouTube Channel👉\nFollow us on Social Media for Latest Updates :\nFacebook : \nInstagram : \nX (Twitter)  : \nMinmini     :  \nWhatsapp Channel :  \nShareChat : \nTelegram :",
    "thumbnails": {
      "default": {
        "url": "https://i.ytimg.com/vi/EOL6Id55wq8/default.jpg",
        "width": 120,
        "height": 90
      },
      "medium": {
        "url": "https://i.ytimg.com/vi/EOL6Id55wq8/mqdefault.jpg",
        "width": 320,
        "height": 180
      },
      "high": {
        "url": "https://i.ytimg.com/vi/EOL6Id55wq8/hqdefault.jpg",
        "width": 480,
        "height": 360
      },
      "standard": {
        "url": "https://i.ytimg.com/vi/EOL6Id55wq8/sddefault.jpg",
        "width": 640,
        "height": 480
      },
      "maxres": {
        "url": "https://i.ytimg.com/vi/EOL6Id55wq8/maxresdefault.jpg",
        "width": 1280,
        "height": 720
      }
    },
    "playlistId": "PLkdhKIzS8nUlgYeQhV3UY4ibQ0nAGuK1y",
    "publishedAt": "2025-09-17T10:09:49Z",
    "channelTitle": "Thanthi One",
    "videoOwnerChannelTitle": "Thanthi One",
    "videoOwnerChannelId": "UCFYqIFxANnSDsnz6qDH01Hw",
    "duration": "PT1H23M42S"
  },
  {
    "id": "1aZUKvLQ5e0",
    "title": "Red Ghost - திக்திக் மர்மங்களுடன் Action திரைப்படம்🎬| Super Hit Cinema | Thanthi one | 6th January",
    "description": "A mysterious lone warrior, the Red Ghost, stalks and eliminates Nazi soldiers in the Russian wilderness. A group of Soviet soldiers, stranded behind enemy lines, find themselves besieged by a Wehrmacht unit at a remote farm. The Red Ghost joins forces with the Soviet soldiers to take down their common enemy in a desperate fight for survival.\nTo Watch Super Hit Cinemas : \nDon't forget to SUBSCRIBE Thanthi One YouTube Channel👉\nFollow us on Social Media for Latest Updates :\nFacebook : \nInstagram : \nX (Twitter)  : \nMinmini     :  \nWhatsapp Channel :  \nShareChat : \nTelegram :",
    "thumbnails": {
      "default": {
        "url": "https://i.ytimg.com/vi/1aZUKvLQ5e0/default.jpg",
        "width": 120,
        "height": 90
      },
      "medium": {
        "url": "https://i.ytimg.com/vi/1aZUKvLQ5e0/mqdefault.jpg",
        "width": 320,
        "height": 180
      },
      "high": {
        "url": "https://i.ytimg.com/vi/1aZUKvLQ5e0/hqdefault.jpg",
        "width": 480,
        "height": 360
      },
      "standard": {
        "url": "https://i.ytimg.com/vi/1aZUKvLQ5e0/sddefault.jpg",
        "width": 640,
        "height": 480
      },
      "maxres": {
        "url": "https://i.ytimg.com/vi/1aZUKvLQ5e0/maxresdefault.jpg",
        "width": 1280,
        "height": 720
      }
    },
    "playlistId": "PLkdhKIzS8nUlgYeQhV3UY4ibQ0nAGuK1y",
    "publishedAt": "2025-09-17T10:09:49Z",
    "channelTitle": "Thanthi One",
    "videoOwnerChannelTitle": "Thanthi One",
    "videoOwnerChannelId": "UCFYqIFxANnSDsnz6qDH01Hw",
    "duration": "PT1H24M4S"
  },
  {
    "id": "OnVGLxDJO6U",
    "title": "See for Me - மிரளவைக்கும் திகில் திரைப்படம்🎬| Super Hit Cinema | Thanthi one | 5th January",
    "description": "Downhill skier Sophie Scott's Olympic dreams are shattered by a degenerative eye disease. Forced to adapt, she takes on a cat-sitting job, but soon finds herself in a desperate fight for survival when the house is targeted by thieves. With the help of Kelly, a sighted gamer, Sophie outsmarts the robbers and regains her determination to pursue the Paralympics.\nTo Watch Super Hit Cinemas : \nDon't forget to SUBSCRIBE Thanthi One YouTube Channel👉\nFollow us on Social Media for Latest Updates :\nFacebook : \nInstagram : \nX (Twitter)  : \nMinmini     :  \nWhatsapp Channel :  \nShareChat : \nTelegram :",
    "thumbnails": {
      "default": {
        "url": "https://i.ytimg.com/vi/OnVGLxDJO6U/default.jpg",
        "width": 120,
        "height": 90
      },
      "medium": {
        "url": "https://i.ytimg.com/vi/OnVGLxDJO6U/mqdefault.jpg",
        "width": 320,
        "height": 180
      },
      "high": {
        "url": "https://i.ytimg.com/vi/OnVGLxDJO6U/hqdefault.jpg",
        "width": 480,
        "height": 360
      },
      "standard": {
        "url": "https://i.ytimg.com/vi/OnVGLxDJO6U/sddefault.jpg",
        "width": 640,
        "height": 480
      },
      "maxres": {
        "url": "https://i.ytimg.com/vi/OnVGLxDJO6U/maxresdefault.jpg",
        "width": 1280,
        "height": 720
      }
    },
    "playlistId": "PLkdhKIzS8nUlgYeQhV3UY4ibQ0nAGuK1y",
    "publishedAt": "2025-09-17T10:09:49Z",
    "channelTitle": "Thanthi One",
    "videoOwnerChannelTitle": "Thanthi One",
    "videoOwnerChannelId": "UCFYqIFxANnSDsnz6qDH01Hw",
    "duration": "PT1H22M17S"
  },
  {
    "id": "YWtQ4bQ2aPc",
    "title": "The Grandson - மர்மம் நிறைந்த Thriller திரைப்படம்🎬| Super Hit Cinema | Thanthi one | 4th January",
    "description": "A young man inherits his grandfather's farm and must navigate the complexities of love, loss, and legacy. He struggles to balance his own aspirations with his family's expectations, fearing he may disappoint them. Ultimately, he seeks to find a way to respect his family's history while forging his own path.\nTo Watch Super Hit Cinemas : \nDon't forget to SUBSCRIBE Thanthi One YouTube Channel👉\nFollow us on Social Media for Latest Updates :\nFacebook : \nInstagram : \nX (Twitter)  : \nMinmini     :  \nWhatsapp Channel :  \nShareChat : \nTelegram :",
    "thumbnails": {
      "default": {
        "url": "https://i.ytimg.com/vi/YWtQ4bQ2aPc/default.jpg",
        "width": 120,
        "height": 90
      },
      "medium": {
        "url": "https://i.ytimg.com/vi/YWtQ4bQ2aPc/mqdefault.jpg",
        "width": 320,
        "height": 180
      },
      "high": {
        "url": "https://i.ytimg.com/vi/YWtQ4bQ2aPc/hqdefault.jpg",
        "width": 480,
        "height": 360
      },
      "standard": {
        "url": "https://i.ytimg.com/vi/YWtQ4bQ2aPc/sddefault.jpg",
        "width": 640,
        "height": 480
      },
      "maxres": {
        "url": "https://i.ytimg.com/vi/YWtQ4bQ2aPc/maxresdefault.jpg",
        "width": 1280,
        "height": 720
      }
    },
    "playlistId": "PLkdhKIzS8nUlgYeQhV3UY4ibQ0nAGuK1y",
    "publishedAt": "2025-09-17T10:09:49Z",
    "channelTitle": "Thanthi One",
    "videoOwnerChannelTitle": "Thanthi One",
    "videoOwnerChannelId": "UCFYqIFxANnSDsnz6qDH01Hw",
    "duration": "PT1H48M51S"
  },
  {
    "id": "_B3RSip8kNA",
    "title": "Post Mortem - திக்திக் மர்மங்களுடன் திகில் திரைப்படம்🎬| Super Hit Cinema | Thanthi One | 2nd January",
    "description": "After a near-death experience in WWI, photographer Tomás captures portraits of the living and dead. In a Hungarian village ravaged by pandemic, he meets 10-year-old Anna and together they explore the spirit world, confronting supernatural forces.\nTo Watch Super Hit Cinemas : \nDon't forget to SUBSCRIBE Thanthi One YouTube Channel👉\nFollow us on Social Media for Latest Updates :\nFacebook : \nInstagram : \nX (Twitter)  : \nMinmini     :  \nWhatsapp Channel :  \nShareChat : \nTelegram :",
    "thumbnails": {
      "default": {
        "url": "https://i.ytimg.com/vi/_B3RSip8kNA/default.jpg",
        "width": 120,
        "height": 90
      },
      "medium": {
        "url": "https://i.ytimg.com/vi/_B3RSip8kNA/mqdefault.jpg",
        "width": 320,
        "height": 180
      },
      "high": {
        "url": "https://i.ytimg.com/vi/_B3RSip8kNA/hqdefault.jpg",
        "width": 480,
        "height": 360
      },
      "standard": {
        "url": "https://i.ytimg.com/vi/_B3RSip8kNA/sddefault.jpg",
        "width": 640,
        "height": 480
      },
      "maxres": {
        "url": "https://i.ytimg.com/vi/_B3RSip8kNA/maxresdefault.jpg",
        "width": 1280,
        "height": 720
      }
    },
    "playlistId": "PLkdhKIzS8nUlgYeQhV3UY4ibQ0nAGuK1y",
    "publishedAt": "2025-09-17T10:09:49Z",
    "channelTitle": "Thanthi One",
    "videoOwnerChannelTitle": "Thanthi One",
    "videoOwnerChannelId": "UCFYqIFxANnSDsnz6qDH01Hw",
    "duration": "PT1H45M19S"
  },
  {
    "id": "GxZvwYI9uDw",
    "title": "Virali - மோகன்லால் / நயன்தாரா நடித்த திகில் திரைப்படம்🔥|Super Hit Cinema| Thanthi One| 25th December",
    "description": "Sreekumar reunites with his school friend Govindan Kutty and meets Rita Mathews, a mysterious girl he mistakenly thinks is a prostitute. However, Rita is actually the spirit of a Medical College student who disappeared. Sreekumar, the only one who can see her, teams up with his friends and Rita's spirit to solve the mystery of her vanishing.\nTo Watch Super Hit Cinemas : \nDon't forget to SUBSCRIBE Thanthi One YouTube Channel👉\nFollow us on Social Media for Latest Updates :\nFacebook : \nInstagram : \nX (Twitter)  : \nMinmini     :  \nWhatsapp Channel :  \nShareChat : \nTelegram :",
    "thumbnails": {
      "default": {
        "url": "https://i.ytimg.com/vi/GxZvwYI9uDw/default.jpg",
        "width": 120,
        "height": 90
      },
      "medium": {
        "url": "https://i.ytimg.com/vi/GxZvwYI9uDw/mqdefault.jpg",
        "width": 320,
        "height": 180
      },
      "high": {
        "url": "https://i.ytimg.com/vi/GxZvwYI9uDw/hqdefault.jpg",
        "width": 480,
        "height": 360
      },
      "standard": {
        "url": "https://i.ytimg.com/vi/GxZvwYI9uDw/sddefault.jpg",
        "width": 640,
        "height": 480
      },
      "maxres": {
        "url": "https://i.ytimg.com/vi/GxZvwYI9uDw/maxresdefault.jpg",
        "width": 1280,
        "height": 720
      }
    },
    "playlistId": "PLkdhKIzS8nUlgYeQhV3UY4ibQ0nAGuK1y",
    "publishedAt": "2025-09-17T10:09:49Z",
    "channelTitle": "Thanthi One",
    "videoOwnerChannelTitle": "Thanthi One",
    "videoOwnerChannelId": "UCFYqIFxANnSDsnz6qDH01Hw",
    "duration": "PT2H19M6S"
  },
  {
    "id": "OYDzAqwEZ2o",
    "title": "The White Storm 2 - மர்மம் நிறைந்த Thriller திரைப்படம்🎬 |Super Hit Cinema|Thanthi One| 21st December",
    "description": "Yu Shun-tin, a former triad member, seeks revenge against the drug lord Jizo after his son dies from an overdose. The conflict escalates, claiming the lives of Yu's wife and ultimately, Yu and Jizo themselves in a deadly subway shootout. Police Inspector Lam honors Yu's legacy by using his bounty to help children of drug addicts.\nTo Watch Super Hit Cinemas : \nDon't forget to SUBSCRIBE Thanthi One YouTube Channel👉\nFollow us on Social Media for Latest Updates :\nFacebook : \nInstagram : \nX (Twitter)  : \nMinmini     :  \nWhatsapp Channel :  \nShareChat : \nTelegram :",
    "thumbnails": {
      "default": {
        "url": "https://i.ytimg.com/vi/OYDzAqwEZ2o/default.jpg",
        "width": 120,
        "height": 90
      },
      "medium": {
        "url": "https://i.ytimg.com/vi/OYDzAqwEZ2o/mqdefault.jpg",
        "width": 320,
        "height": 180
      },
      "high": {
        "url": "https://i.ytimg.com/vi/OYDzAqwEZ2o/hqdefault.jpg",
        "width": 480,
        "height": 360
      },
      "standard": {
        "url": "https://i.ytimg.com/vi/OYDzAqwEZ2o/sddefault.jpg",
        "width": 640,
        "height": 480
      },
      "maxres": {
        "url": "https://i.ytimg.com/vi/OYDzAqwEZ2o/maxresdefault.jpg",
        "width": 1280,
        "height": 720
      }
    },
    "playlistId": "PLkdhKIzS8nUlgYeQhV3UY4ibQ0nAGuK1y",
    "publishedAt": "2025-09-17T10:09:49Z",
    "channelTitle": "Thanthi One",
    "videoOwnerChannelTitle": "Thanthi One",
    "videoOwnerChannelId": "UCFYqIFxANnSDsnz6qDH01Hw",
    "duration": "PT1H20M6S"
  },
  {
    "id": "b08lLhkz2x4",
    "title": "Reset - மர்மங்கள் மிரட்டும் Thriller திரைப்படம்🎬| Super Hit Cinema | Thanthi One | 15th December",
    "description": "Xia Tian, a single mother and scientist, uses her time travel machine to rescue her kidnapped son, Dou Dou, from the clutches of the mastermind behind the plot: her research director. As she travels back in time, Xia Tian encounters past versions of herself, leading to unforeseen consequences and alternate timelines. Will Xia Tian's sacrifices ultimately save her son, and what fate awaits the multiple versions of herself?\nTo Watch Super Hit Cinemas : \nDon't forget to SUBSCRIBE Thanthi One YouTube Channel👉\nFollow us on Social Media for Latest Updates :\nFacebook : \nInstagram : \nX (Twitter)  : \nMinmini     :  \nWhatsapp Channel :  \nShareChat : \nTelegram :",
    "thumbnails": {
      "default": {
        "url": "https://i.ytimg.com/vi/b08lLhkz2x4/default.jpg",
        "width": 120,
        "height": 90
      },
      "medium": {
        "url": "https://i.ytimg.com/vi/b08lLhkz2x4/mqdefault.jpg",
        "width": 320,
        "height": 180
      },
      "high": {
        "url": "https://i.ytimg.com/vi/b08lLhkz2x4/hqdefault.jpg",
        "width": 480,
        "height": 360
      },
      "standard": {
        "url": "https://i.ytimg.com/vi/b08lLhkz2x4/sddefault.jpg",
        "width": 640,
        "height": 480
      },
      "maxres": {
        "url": "https://i.ytimg.com/vi/b08lLhkz2x4/maxresdefault.jpg",
        "width": 1280,
        "height": 720
      }
    },
    "playlistId": "PLkdhKIzS8nUlgYeQhV3UY4ibQ0nAGuK1y",
    "publishedAt": "2025-09-17T10:09:49Z",
    "channelTitle": "Thanthi One",
    "videoOwnerChannelTitle": "Thanthi One",
    "videoOwnerChannelId": "UCFYqIFxANnSDsnz6qDH01Hw",
    "duration": "PT1H34M15S"
  },
  {
    "id": "7HeVaprv92g",
    "title": "Boot Sound - திக்திக் மர்மங்களுடன் Thriller திரைப்படம்| Super Hit Cinema| Thanthi One| 14th December",
    "description": "A retired police officer's murder sparks a tale of vengeance. Sankaranarayanan, driven by a tragic past, targets retired officers who wronged him. Justice takes a shocking turn as the cycle of revenge unfolds.\nTo Watch Super Hit Cinemas : \nDon't forget to SUBSCRIBE Thanthi One YouTube Channel👉\nFollow us on Social Media for Latest Updates :\nFacebook : \nInstagram : \nX (Twitter)  : \nMinmini     :  \nWhatsapp Channel :  \nShareChat : \nTelegram :",
    "thumbnails": {
      "default": {
        "url": "https://i.ytimg.com/vi/7HeVaprv92g/default.jpg",
        "width": 120,
        "height": 90
      },
      "medium": {
        "url": "https://i.ytimg.com/vi/7HeVaprv92g/mqdefault.jpg",
        "width": 320,
        "height": 180
      },
      "high": {
        "url": "https://i.ytimg.com/vi/7HeVaprv92g/hqdefault.jpg",
        "width": 480,
        "height": 360
      },
      "standard": {
        "url": "https://i.ytimg.com/vi/7HeVaprv92g/sddefault.jpg",
        "width": 640,
        "height": 480
      },
      "maxres": {
        "url": "https://i.ytimg.com/vi/7HeVaprv92g/maxresdefault.jpg",
        "width": 1280,
        "height": 720
      }
    },
    "playlistId": "PLkdhKIzS8nUlgYeQhV3UY4ibQ0nAGuK1y",
    "publishedAt": "2025-09-17T10:09:49Z",
    "channelTitle": "Thanthi One",
    "videoOwnerChannelTitle": "Thanthi One",
    "videoOwnerChannelId": "UCFYqIFxANnSDsnz6qDH01Hw",
    "duration": "PT1H43M51S"
  },
  {
    "id": "VKFl8WB63JQ",
    "title": "The Power - திக்திக் மர்மங்களுடன் Thriller திரைப்படம்🎬 | Super Hit Cinema|Thanthi One| 10th December",
    "description": "In 1970s London, a young nurse's first night shift at the East London Royal Infirmary turns sinister when a power outage sparks by a miners' strike plunges her into darkness. Haunted by supernatural presence and her own troubled past in an orphanage, she must confront her darkest fears.\nTo Watch Super Hit Cinemas : \nDon't forget to SUBSCRIBE Thanthi One YouTube Channel👉\nFollow us on Social Media for Latest Updates :\nFacebook : \nInstagram : \nX (Twitter)  : \nMinmini     :  \nWhatsapp Channel :  \nShareChat : \nTelegram :",
    "thumbnails": {
      "default": {
        "url": "https://i.ytimg.com/vi/VKFl8WB63JQ/default.jpg",
        "width": 120,
        "height": 90
      },
      "medium": {
        "url": "https://i.ytimg.com/vi/VKFl8WB63JQ/mqdefault.jpg",
        "width": 320,
        "height": 180
      },
      "high": {
        "url": "https://i.ytimg.com/vi/VKFl8WB63JQ/hqdefault.jpg",
        "width": 480,
        "height": 360
      },
      "standard": {
        "url": "https://i.ytimg.com/vi/VKFl8WB63JQ/sddefault.jpg",
        "width": 640,
        "height": 480
      },
      "maxres": {
        "url": "https://i.ytimg.com/vi/VKFl8WB63JQ/maxresdefault.jpg",
        "width": 1280,
        "height": 720
      }
    },
    "playlistId": "PLkdhKIzS8nUlgYeQhV3UY4ibQ0nAGuK1y",
    "publishedAt": "2025-09-17T10:09:49Z",
    "channelTitle": "Thanthi One",
    "videoOwnerChannelTitle": "Thanthi One",
    "videoOwnerChannelId": "UCFYqIFxANnSDsnz6qDH01Hw",
    "duration": "PT1H25M48S"
  },
  {
    "id": "Gx9O17deuoI",
    "title": "Target Number One - மர்மம் நிறைந்த Thriller திரைப்படம்🎬| Super Hit Cinema| Thanthi One| 8th December",
    "description": "Based on a true 1989 story, a Canadian journalist, Victor Malarek, investigates the wrongful conviction of Daniel Léger, a heroin addict framed by dealer Glen Picker. Malarek's exposé sparks an ethics probe, while Léger, sentenced to 100 years in Thai prison, transforms himself, overcoming addiction and securing a transfer to Canada. Amidst justice served, corruption prevails unpunished.\nTo Watch Super Hit Cinemas : \nDon't forget to SUBSCRIBE Thanthi One YouTube Channel👉\nFollow us on Social Media for Latest Updates :\nFacebook : \nInstagram : \nX (Twitter)  : \nMinmini     :  \nWhatsapp Channel :  \nShareChat : \nTelegram :",
    "thumbnails": {
      "default": {
        "url": "https://i.ytimg.com/vi/Gx9O17deuoI/default.jpg",
        "width": 120,
        "height": 90
      },
      "medium": {
        "url": "https://i.ytimg.com/vi/Gx9O17deuoI/mqdefault.jpg",
        "width": 320,
        "height": 180
      },
      "high": {
        "url": "https://i.ytimg.com/vi/Gx9O17deuoI/hqdefault.jpg",
        "width": 480,
        "height": 360
      },
      "standard": {
        "url": "https://i.ytimg.com/vi/Gx9O17deuoI/sddefault.jpg",
        "width": 640,
        "height": 480
      },
      "maxres": {
        "url": "https://i.ytimg.com/vi/Gx9O17deuoI/maxresdefault.jpg",
        "width": 1280,
        "height": 720
      }
    },
    "playlistId": "PLkdhKIzS8nUlgYeQhV3UY4ibQ0nAGuK1y",
    "publishedAt": "2025-09-17T10:09:49Z",
    "channelTitle": "Thanthi One",
    "videoOwnerChannelTitle": "Thanthi One",
    "videoOwnerChannelId": "UCFYqIFxANnSDsnz6qDH01Hw",
    "duration": "PT1H49M18S"
  },
  {
    "id": "HqjlsXnNLKA",
    "title": "Bill Gates - திகில் காமெடி கலந்த திரைப்படம்🔥| Super Hit Cinema | Thanthi One | 1st December",
    "description": "Two mischievous boys, Pandu and Kiri, are inspired by Bill Gates' story and dream of becoming successful entrepreneurs in Bengaluru. As they navigate challenges and opportunities, they secure jobs at a software company and a chance to travel to the USA. But their journey takes a spooky turn when they discover their bungalow is haunted by a vengeful ghost.\nTo Watch Super Hit Cinemas : \nDon't forget to SUBSCRIBE Thanthi One YouTube Channel👉\nFollow us on Social Media for Latest Updates :\nFacebook : \nInstagram : \nX (Twitter)  : \nMinmini     :  \nWhatsapp Channel :  \nShareChat : \nTelegram :",
    "thumbnails": {
      "default": {
        "url": "https://i.ytimg.com/vi/HqjlsXnNLKA/default.jpg",
        "width": 120,
        "height": 90
      },
      "medium": {
        "url": "https://i.ytimg.com/vi/HqjlsXnNLKA/mqdefault.jpg",
        "width": 320,
        "height": 180
      },
      "high": {
        "url": "https://i.ytimg.com/vi/HqjlsXnNLKA/hqdefault.jpg",
        "width": 480,
        "height": 360
      },
      "standard": {
        "url": "https://i.ytimg.com/vi/HqjlsXnNLKA/sddefault.jpg",
        "width": 640,
        "height": 480
      },
      "maxres": {
        "url": "https://i.ytimg.com/vi/HqjlsXnNLKA/maxresdefault.jpg",
        "width": 1280,
        "height": 720
      }
    },
    "playlistId": "PLkdhKIzS8nUlgYeQhV3UY4ibQ0nAGuK1y",
    "publishedAt": "2025-09-17T10:09:49Z",
    "channelTitle": "Thanthi One",
    "videoOwnerChannelTitle": "Thanthi One",
    "videoOwnerChannelId": "UCFYqIFxANnSDsnz6qDH01Hw",
    "duration": "PT1H52M57S"
  },
  {
    "id": "3aouAK07KH8",
    "title": "Swarasiyam - மர்மம் நிறைந்த Thriller திரைப்படம்🔥| Super Hit Cinema | Thanthi One | 12th November",
    "description": "Shambu Shetty, a novelist-turned-gunman, whose shocking transformation sets off a mysterious chain of events. His actions entangle Yakshagana artist Harsha, Uma, and Mohana in a web of suspense, romance, and moral dilemmas.\nTo Watch Super Hit Cinemas : \nDon't forget to SUBSCRIBE Thanthi One YouTube Channel👉\nFollow us on Social Media for Latest Updates :\nFacebook : \nInstagram : \nX (Twitter)  : \nMinmini     :  \nWhatsapp Channel :  \nShareChat : \nTelegram :",
    "thumbnails": {
      "default": {
        "url": "https://i.ytimg.com/vi/3aouAK07KH8/default.jpg",
        "width": 120,
        "height": 90
      },
      "medium": {
        "url": "https://i.ytimg.com/vi/3aouAK07KH8/mqdefault.jpg",
        "width": 320,
        "height": 180
      },
      "high": {
        "url": "https://i.ytimg.com/vi/3aouAK07KH8/hqdefault.jpg",
        "width": 480,
        "height": 360
      },
      "standard": {
        "url": "https://i.ytimg.com/vi/3aouAK07KH8/sddefault.jpg",
        "width": 640,
        "height": 480
      },
      "maxres": {
        "url": "https://i.ytimg.com/vi/3aouAK07KH8/maxresdefault.jpg",
        "width": 1280,
        "height": 720
      }
    },
    "playlistId": "PLkdhKIzS8nUlgYeQhV3UY4ibQ0nAGuK1y",
    "publishedAt": "2025-09-17T10:09:49Z",
    "channelTitle": "Thanthi One",
    "videoOwnerChannelTitle": "Thanthi One",
    "videoOwnerChannelId": "UCFYqIFxANnSDsnz6qDH01Hw",
    "duration": "PT2H10M44S"
  },
  {
    "id": "pi-jumnVPqc",
    "title": "Dwipatra - மர்மம் நிறைந்த Thriller திரைப்படம்🔥| Super Hit Cinema | Thanthi One | 1st November",
    "description": "In a chilling spree, a calculating killer targets the daughters of influential figures, leaving behind only haunting notes. As the body count rises, the police, CBI, and detectives race against time to unravel the mystery. But every lead ends in frustration, every clue in despair. Will the killer's cunning prove too great, or will determination and justice ultimately prevail?\nTo Watch Super Hit Cinemas : \nDon't forget to SUBSCRIBE Thanthi One YouTube Channel👉\nFollow us on Social Media for Latest Updates :\nFacebook : \nInstagram : \nX (Twitter)  : \nMinmini     :  \nWhatsapp Channel :  \nShareChat : \nTelegram :",
    "thumbnails": {
      "default": {
        "url": "https://i.ytimg.com/vi/pi-jumnVPqc/default.jpg",
        "width": 120,
        "height": 90
      },
      "medium": {
        "url": "https://i.ytimg.com/vi/pi-jumnVPqc/mqdefault.jpg",
        "width": 320,
        "height": 180
      },
      "high": {
        "url": "https://i.ytimg.com/vi/pi-jumnVPqc/hqdefault.jpg",
        "width": 480,
        "height": 360
      },
      "standard": {
        "url": "https://i.ytimg.com/vi/pi-jumnVPqc/sddefault.jpg",
        "width": 640,
        "height": 480
      },
      "maxres": {
        "url": "https://i.ytimg.com/vi/pi-jumnVPqc/maxresdefault.jpg",
        "width": 1280,
        "height": 720
      }
    },
    "playlistId": "PLkdhKIzS8nUlgYeQhV3UY4ibQ0nAGuK1y",
    "publishedAt": "2025-09-17T10:09:49Z",
    "channelTitle": "Thanthi One",
    "videoOwnerChannelTitle": "Thanthi One",
    "videoOwnerChannelId": "UCFYqIFxANnSDsnz6qDH01Hw",
    "duration": "PT1H42M49S"
  },
  {
    "id": "STImeEHqqOs",
    "title": "Looking Glass - மர்மங்கள் நிறைந்த Thriller திரைப்படம்🎬| Super Hit Cinema | Thanthi One| 28th October",
    "description": "Ray and Maggie escape their grief by buying a remote California desert motel, but Ray's discovery of a one-way mirror in Room 10 reveals dark secrets. A gruesome murder and suspicious locals, especially Deputy Sheriff Howard, fuel Ray's paranoia. In a thrilling climax, Ray rescues Maggie from Howard's clutches, defeating him to escape the motel's deadly trap.\nTo Watch Super Hit Cinemas : \nDon't forget to SUBSCRIBE Thanthi One YouTube Channel👉\nFollow us on Social Media for Latest Updates :\nFacebook : \nInstagram : \nX (Twitter)  : \nMinmini     :  \nWhatsapp Channel :  \nShareChat : \nTelegram :",
    "thumbnails": {
      "default": {
        "url": "https://i.ytimg.com/vi/STImeEHqqOs/default.jpg",
        "width": 120,
        "height": 90
      },
      "medium": {
        "url": "https://i.ytimg.com/vi/STImeEHqqOs/mqdefault.jpg",
        "width": 320,
        "height": 180
      },
      "high": {
        "url": "https://i.ytimg.com/vi/STImeEHqqOs/hqdefault.jpg",
        "width": 480,
        "height": 360
      },
      "standard": {
        "url": "https://i.ytimg.com/vi/STImeEHqqOs/sddefault.jpg",
        "width": 640,
        "height": 480
      },
      "maxres": {
        "url": "https://i.ytimg.com/vi/STImeEHqqOs/maxresdefault.jpg",
        "width": 1280,
        "height": 720
      }
    },
    "playlistId": "PLkdhKIzS8nUlgYeQhV3UY4ibQ0nAGuK1y",
    "publishedAt": "2025-09-17T10:09:49Z",
    "channelTitle": "Thanthi One",
    "videoOwnerChannelTitle": "Thanthi One",
    "videoOwnerChannelId": "UCFYqIFxANnSDsnz6qDH01Hw",
    "duration": "PT1H30M36S"
  },
  {
    "id": "UamfWaaHn4Y",
    "title": "Half Stories - மிரளவைக்கும் திகில் திரைப்படம்🔥| Super Hit Cinema | Thanthi One | 26th October",
    "description": "Lakshmi, Chinna, and Shiva, inseparable friends and partners in organized crime, face turmoil when a high-stakes heist goes awry. Missing money fuels distrust; each friend suspects betrayal, straining their bond and loyalty. Tension escalates as they investigate, confronting their darkest fears: have they been deceived by one of their own?\nTo Watch Super Hit Cinemas : \nDon't forget to SUBSCRIBE Thanthi One YouTube Channel👉\nFollow us on Social Media for Latest Updates :\nFacebook : \nInstagram : \nX (Twitter)  : \nMinmini     :  \nWhatsapp Channel :  \nShareChat : \nTelegram :",
    "thumbnails": {
      "default": {
        "url": "https://i.ytimg.com/vi/UamfWaaHn4Y/default.jpg",
        "width": 120,
        "height": 90
      },
      "medium": {
        "url": "https://i.ytimg.com/vi/UamfWaaHn4Y/mqdefault.jpg",
        "width": 320,
        "height": 180
      },
      "high": {
        "url": "https://i.ytimg.com/vi/UamfWaaHn4Y/hqdefault.jpg",
        "width": 480,
        "height": 360
      },
      "standard": {
        "url": "https://i.ytimg.com/vi/UamfWaaHn4Y/sddefault.jpg",
        "width": 640,
        "height": 480
      },
      "maxres": {
        "url": "https://i.ytimg.com/vi/UamfWaaHn4Y/maxresdefault.jpg",
        "width": 1280,
        "height": 720
      }
    },
    "playlistId": "PLkdhKIzS8nUlgYeQhV3UY4ibQ0nAGuK1y",
    "publishedAt": "2025-09-17T10:09:49Z",
    "channelTitle": "Thanthi One",
    "videoOwnerChannelTitle": "Thanthi One",
    "videoOwnerChannelId": "UCFYqIFxANnSDsnz6qDH01Hw",
    "duration": "PT1H25M17S"
  },
  {
    "id": "eobfGRMpSbc",
    "title": "Consecration - மர்மங்கள் மிரட்டும் Horror திரைப்படம்🎬| Super Hit Cinema | Thanthi One | 5th October",
    "description": "Jena Malone plays Grace, driven to unravel the enigmatic death of her priest brother at a secluded Scottish convent. Skeptical of the Church's claims, she uncovers a labyrinth of darkness, including murder, blasphemy, and shocking revelations that shatter her perceptions of faith and reality.\nClick To Watch Super Hit Cinemas : \nDon't forget to SUBSCRIBE Thanthi One YouTube Channel👉\nFollow us on Social Media for Latest Updates :\nFacebook : \nInstagram : \nX (Twitter)  : \nMinmini     :  \nWhatsapp Channel :  \nShareChat : \nTelegram :",
    "thumbnails": {
      "default": {
        "url": "https://i.ytimg.com/vi/eobfGRMpSbc/default.jpg",
        "width": 120,
        "height": 90
      },
      "medium": {
        "url": "https://i.ytimg.com/vi/eobfGRMpSbc/mqdefault.jpg",
        "width": 320,
        "height": 180
      },
      "high": {
        "url": "https://i.ytimg.com/vi/eobfGRMpSbc/hqdefault.jpg",
        "width": 480,
        "height": 360
      },
      "standard": {
        "url": "https://i.ytimg.com/vi/eobfGRMpSbc/sddefault.jpg",
        "width": 640,
        "height": 480
      },
      "maxres": {
        "url": "https://i.ytimg.com/vi/eobfGRMpSbc/maxresdefault.jpg",
        "width": 1280,
        "height": 720
      }
    },
    "playlistId": "PLkdhKIzS8nUlgYeQhV3UY4ibQ0nAGuK1y",
    "publishedAt": "2025-09-17T10:09:49Z",
    "channelTitle": "Thanthi One",
    "videoOwnerChannelTitle": "Thanthi One",
    "videoOwnerChannelId": "UCFYqIFxANnSDsnz6qDH01Hw",
    "duration": "PT1H19M23S"
  },
  {
    "id": "rRHlQpZzP4s",
    "title": "The Free Fall - உலகையே மிரட்டிய Horror  திரைப்படம்🎬| Super Hit Cinema | Thanthi One | 28th September",
    "description": "Sarah witnesses her mother's gruesome murder of her father, then attempts suicide, awakening with hazy memories. Her husband Nick's sinister intentions unfold amidst bizarre events. But Nick's demon possession is exorcised, only to reveal Sarah's sister Julie as the new vessel.\nClick To Watch Super Hit Cinemas : \nDon't forget to SUBSCRIBE Thanthi One YouTube Channel👉\nFollow us on Social Media for Latest Updates :\nFacebook : \nInstagram : \nX (Twitter)  : \nMinmini     :  \nWhatsapp Channel :  \nShareChat : \nTelegram :",
    "thumbnails": {
      "default": {
        "url": "https://i.ytimg.com/vi/rRHlQpZzP4s/default.jpg",
        "width": 120,
        "height": 90
      },
      "medium": {
        "url": "https://i.ytimg.com/vi/rRHlQpZzP4s/mqdefault.jpg",
        "width": 320,
        "height": 180
      },
      "high": {
        "url": "https://i.ytimg.com/vi/rRHlQpZzP4s/hqdefault.jpg",
        "width": 480,
        "height": 360
      },
      "standard": {
        "url": "https://i.ytimg.com/vi/rRHlQpZzP4s/sddefault.jpg",
        "width": 640,
        "height": 480
      },
      "maxres": {
        "url": "https://i.ytimg.com/vi/rRHlQpZzP4s/maxresdefault.jpg",
        "width": 1280,
        "height": 720
      }
    },
    "playlistId": "PLkdhKIzS8nUlgYeQhV3UY4ibQ0nAGuK1y",
    "publishedAt": "2025-09-17T10:09:49Z",
    "channelTitle": "Thanthi One",
    "videoOwnerChannelTitle": "Thanthi One",
    "videoOwnerChannelId": "UCFYqIFxANnSDsnz6qDH01Hw",
    "duration": "PT1H9M59S"
  },
  {
    "id": "3KvEaPO2oN8",
    "title": "Bairavan - மர்மங்கள் மிரட்டும் Thriller திரைப்படம்🔥| Super Hit Cinema | Thanthi One | 20th September",
    "description": "Unravel a sinister plot of murder, deceit, and suspicion. Four enigmatic suspects emerge, but are they masterminds or pawns? Fear and paranoia grip the village, blurring reality and illusion. Is evil lurking or are villagers' darkest fears conjuring monsters?\nClick To watch Super Hit Cinemas : \nDon't forget to SUBSCRIBE Thanthi One YouTube Channel👉\nFollow us on Social Media for Latest Updates :\nFacebook : \nInstagram : \nX (Twitter)  : \nMinmini     :  \nWhatsapp Channel :  \nShareChat : \nTelegram :",
    "thumbnails": {
      "default": {
        "url": "https://i.ytimg.com/vi/3KvEaPO2oN8/default.jpg",
        "width": 120,
        "height": 90
      },
      "medium": {
        "url": "https://i.ytimg.com/vi/3KvEaPO2oN8/mqdefault.jpg",
        "width": 320,
        "height": 180
      },
      "high": {
        "url": "https://i.ytimg.com/vi/3KvEaPO2oN8/hqdefault.jpg",
        "width": 480,
        "height": 360
      },
      "standard": {
        "url": "https://i.ytimg.com/vi/3KvEaPO2oN8/sddefault.jpg",
        "width": 640,
        "height": 480
      },
      "maxres": {
        "url": "https://i.ytimg.com/vi/3KvEaPO2oN8/maxresdefault.jpg",
        "width": 1280,
        "height": 720
      }
    },
    "playlistId": "PLkdhKIzS8nUlgYeQhV3UY4ibQ0nAGuK1y",
    "publishedAt": "2025-09-17T10:09:49Z",
    "channelTitle": "Thanthi One",
    "videoOwnerChannelTitle": "Thanthi One",
    "videoOwnerChannelId": "UCFYqIFxANnSDsnz6qDH01Hw",
    "duration": "PT2H4M45S"
  },
  {
    "id": "HYhhrHwTsMo",
    "title": "Chengalpattu - திக்திக் பக்பக் Thriller திரைப்படம்🔥| Super Hit Cinema | Thanthi One | 11th September",
    "description": "When a college student and her friends stumble upon a murder in a secluded location, they unwittingly become the targets of a ruthless gang of criminals. As the gang relentlessly pursues them, the students must fight for survival and uncover the truth behind the murder. With their lives hanging in the balance, they must use all their wits and resourcefulness to outsmart their pursuers and bring the perpetrators to justice.\nDon't forget to SUBSCRIBE Thanthi One YouTube Channel👉\nFollow us on Social Media for Latest Updates :\nFacebook : \nInstagram : \nX (Twitter)  : \nMinmini     :  \nWhatsapp Channel :  \nShareChat : \nTelegram :",
    "thumbnails": {
      "default": {
        "url": "https://i.ytimg.com/vi/HYhhrHwTsMo/default.jpg",
        "width": 120,
        "height": 90
      },
      "medium": {
        "url": "https://i.ytimg.com/vi/HYhhrHwTsMo/mqdefault.jpg",
        "width": 320,
        "height": 180
      },
      "high": {
        "url": "https://i.ytimg.com/vi/HYhhrHwTsMo/hqdefault.jpg",
        "width": 480,
        "height": 360
      },
      "standard": {
        "url": "https://i.ytimg.com/vi/HYhhrHwTsMo/sddefault.jpg",
        "width": 640,
        "height": 480
      },
      "maxres": {
        "url": "https://i.ytimg.com/vi/HYhhrHwTsMo/maxresdefault.jpg",
        "width": 1280,
        "height": 720
      }
    },
    "playlistId": "PLkdhKIzS8nUlgYeQhV3UY4ibQ0nAGuK1y",
    "publishedAt": "2025-09-17T10:09:49Z",
    "channelTitle": "Thanthi One",
    "videoOwnerChannelTitle": "Thanthi One",
    "videoOwnerChannelId": "UCFYqIFxANnSDsnz6qDH01Hw",
    "duration": "PT1H35M31S"
  },
  {
    "id": "GkQaVOXVKqA",
    "title": "Orphan First kill - மிரளவைக்கும் திகில் திரைப்படம்💥| Super Hit Cinema | Thanthi One | 7th September",
    "description": "A 31-year-old woman with a rare disorder escapes a psychiatric institute and impersonates missing girl Esther Albright, infiltrating her family. As she manipulates them, mother Tricia uncovers her true identity, revealing dark secrets. The truth leads to a deadly confrontation, exposing the destructive power of deception and shattered identity.\nTo Watch Super Hit Cinemas : \nDon't forget to SUBSCRIBE Thanthi One YouTube Channel👉\nFollow us on Social Media for Latest Updates :\nFacebook : \nInstagram : \nX (Twitter)  : \nMinmini     :  \nWhatsapp Channel :  \nShareChat : \nTelegram :",
    "thumbnails": {
      "default": {
        "url": "https://i.ytimg.com/vi/GkQaVOXVKqA/default.jpg",
        "width": 120,
        "height": 90
      },
      "medium": {
        "url": "https://i.ytimg.com/vi/GkQaVOXVKqA/mqdefault.jpg",
        "width": 320,
        "height": 180
      },
      "high": {
        "url": "https://i.ytimg.com/vi/GkQaVOXVKqA/hqdefault.jpg",
        "width": 480,
        "height": 360
      },
      "standard": {
        "url": "https://i.ytimg.com/vi/GkQaVOXVKqA/sddefault.jpg",
        "width": 640,
        "height": 480
      },
      "maxres": {
        "url": "https://i.ytimg.com/vi/GkQaVOXVKqA/maxresdefault.jpg",
        "width": 1280,
        "height": 720
      }
    },
    "playlistId": "PLkdhKIzS8nUlgYeQhV3UY4ibQ0nAGuK1y",
    "publishedAt": "2025-09-17T10:09:49Z",
    "channelTitle": "Thanthi One",
    "videoOwnerChannelTitle": "Thanthi One",
    "videoOwnerChannelId": "UCFYqIFxANnSDsnz6qDH01Hw",
    "duration": "PT1H25M33S"
  },
  {
    "id": "_tWNMHTkwg0",
    "title": "Plot - மர்மம் நிறைந்த Thriller திரைப்படம்🔥| Super Hit Cinema | Thanthi One | 31st August",
    "description": "A former failed businessman achieves success in real estate, but his triumph morphs into an all-consuming obsession. He'll stop at nothing to expand his empire, but an anonymous threat emerges, warning him to cease operations. Will his relentless pursuit of success lead to his downfall?\nClick To Watch Super Hit Cinemas : \nDon't forget to SUBSCRIBE Thanthi One YouTube Channel👉\nFollow us on Social Media for Latest Updates :\nFacebook : \nInstagram : \nX (Twitter)  : \nMinmini     :  \nWhatsapp Channel :  \nShareChat : \nTelegram :",
    "thumbnails": {
      "default": {
        "url": "https://i.ytimg.com/vi/_tWNMHTkwg0/default.jpg",
        "width": 120,
        "height": 90
      },
      "medium": {
        "url": "https://i.ytimg.com/vi/_tWNMHTkwg0/mqdefault.jpg",
        "width": 320,
        "height": 180
      },
      "high": {
        "url": "https://i.ytimg.com/vi/_tWNMHTkwg0/hqdefault.jpg",
        "width": 480,
        "height": 360
      },
      "standard": {
        "url": "https://i.ytimg.com/vi/_tWNMHTkwg0/sddefault.jpg",
        "width": 640,
        "height": 480
      },
      "maxres": {
        "url": "https://i.ytimg.com/vi/_tWNMHTkwg0/maxresdefault.jpg",
        "width": 1280,
        "height": 720
      }
    },
    "playlistId": "PLkdhKIzS8nUlgYeQhV3UY4ibQ0nAGuK1y",
    "publishedAt": "2025-09-17T10:09:49Z",
    "channelTitle": "Thanthi One",
    "videoOwnerChannelTitle": "Thanthi One",
    "videoOwnerChannelId": "UCFYqIFxANnSDsnz6qDH01Hw",
    "duration": "PT2H34M43S"
  },
  {
    "id": "5bJGQRNYAWE",
    "title": "Shardula - மிரளவைக்கும் திகில் திரைப்படம்🔥| Super Hit Cinema | Thanthi One | 26th August",
    "description": "In the intriguing movie, four young friends find themselves entwined with the eerie and enigmatic place known as Shardula. As they delve deeper, they begin to question the existence of the paranormal - are ghosts a tangible reality or merely a product of their own vivid imaginations? Dive into the mystery and explore the blurred lines between the unknown and the fabricated.\nClick To Watch Super Hit Cinemas : \nDon't forget to SUBSCRIBE Thanthi One YouTube Channel👉\nFollow us on Social Media for Latest Updates :\nFacebook : \nInstagram : \nX (Twitter)  : \nMinmini     :  \nWhatsapp Channel :  \nShareChat : \nTelegram :",
    "thumbnails": {
      "default": {
        "url": "https://i.ytimg.com/vi/5bJGQRNYAWE/default.jpg",
        "width": 120,
        "height": 90
      },
      "medium": {
        "url": "https://i.ytimg.com/vi/5bJGQRNYAWE/mqdefault.jpg",
        "width": 320,
        "height": 180
      },
      "high": {
        "url": "https://i.ytimg.com/vi/5bJGQRNYAWE/hqdefault.jpg",
        "width": 480,
        "height": 360
      },
      "standard": {
        "url": "https://i.ytimg.com/vi/5bJGQRNYAWE/sddefault.jpg",
        "width": 640,
        "height": 480
      },
      "maxres": {
        "url": "https://i.ytimg.com/vi/5bJGQRNYAWE/maxresdefault.jpg",
        "width": 1280,
        "height": 720
      }
    },
    "playlistId": "PLkdhKIzS8nUlgYeQhV3UY4ibQ0nAGuK1y",
    "publishedAt": "2025-09-17T10:09:49Z",
    "channelTitle": "Thanthi One",
    "videoOwnerChannelTitle": "Thanthi One",
    "videoOwnerChannelId": "UCFYqIFxANnSDsnz6qDH01Hw",
    "duration": "PT2H5M36S"
  },
  {
    "id": "MsQO7NSmGB4",
    "title": "Go Slow - மர்மம் நிறைந்த Thriller திரைப்படம்🔥| Super Hit Cinema | Thanthi One | 13th August",
    "description": "In the gripping tale of Trikona, three strangers - Nataraj, Kodandarama, and Trivikrama - embark on a journey to Mangalore, each driven by their own motivations. When their vehicles coincidentally break down in a remote forest, the enigmatic Kaala emerges, testing their resolve. For 65-year-old Nataraj, patience is his greatest strength, and he must summon it once more to overcome the challenges that lie ahead, armed with nothing but his unwavering determination.\nTo Watch Super Hit Cinemas : \nDon't forget to SUBSCRIBE Thanthi One YouTube Channel👉\nFollow us on Social Media for Latest Updates :\nFacebook : \nInstagram : \nX (Twitter)  : \nWhatsapp Channel :  \nShareChat : \nTelegram :",
    "thumbnails": {
      "default": {
        "url": "https://i.ytimg.com/vi/MsQO7NSmGB4/default.jpg",
        "width": 120,
        "height": 90
      },
      "medium": {
        "url": "https://i.ytimg.com/vi/MsQO7NSmGB4/mqdefault.jpg",
        "width": 320,
        "height": 180
      },
      "high": {
        "url": "https://i.ytimg.com/vi/MsQO7NSmGB4/hqdefault.jpg",
        "width": 480,
        "height": 360
      },
      "standard": {
        "url": "https://i.ytimg.com/vi/MsQO7NSmGB4/sddefault.jpg",
        "width": 640,
        "height": 480
      },
      "maxres": {
        "url": "https://i.ytimg.com/vi/MsQO7NSmGB4/maxresdefault.jpg",
        "width": 1280,
        "height": 720
      }
    },
    "playlistId": "PLkdhKIzS8nUlgYeQhV3UY4ibQ0nAGuK1y",
    "publishedAt": "2025-09-17T10:09:49Z",
    "channelTitle": "Thanthi One",
    "videoOwnerChannelTitle": "Thanthi One",
    "videoOwnerChannelId": "UCFYqIFxANnSDsnz6qDH01Hw",
    "duration": "PT1H58M15S"
  },
  {
    "id": "896aUbRiJGE",
    "title": "Devayanam -  மரணபயம் துரத்தும் Super Hit திரைப்படம்🔥| Super Hit Cinema | Thanthi One | 1st August",
    "description": "An attempt at portraying the life of a widow who is obsessed with the persistent fear of her own death, a term called thanatophobia.\n \nDon't forget to SUBSCRIBE Thanthi One YouTube Channel👉\nFollow us on Social Media for Latest Updates :\nFacebook : \nInstagram : \nX (Twitter)  : \nMinmini     :  \nWhatsapp Channel :  \nShareChat :",
    "thumbnails": {
      "default": {
        "url": "https://i.ytimg.com/vi/896aUbRiJGE/default.jpg",
        "width": 120,
        "height": 90
      },
      "medium": {
        "url": "https://i.ytimg.com/vi/896aUbRiJGE/mqdefault.jpg",
        "width": 320,
        "height": 180
      },
      "high": {
        "url": "https://i.ytimg.com/vi/896aUbRiJGE/hqdefault.jpg",
        "width": 480,
        "height": 360
      },
      "standard": {
        "url": "https://i.ytimg.com/vi/896aUbRiJGE/sddefault.jpg",
        "width": 640,
        "height": 480
      },
      "maxres": {
        "url": "https://i.ytimg.com/vi/896aUbRiJGE/maxresdefault.jpg",
        "width": 1280,
        "height": 720
      }
    },
    "playlistId": "PLkdhKIzS8nUlgYeQhV3UY4ibQ0nAGuK1y",
    "publishedAt": "2025-09-17T10:09:49Z",
    "channelTitle": "Thanthi One",
    "videoOwnerChannelTitle": "Thanthi One",
    "videoOwnerChannelId": "UCFYqIFxANnSDsnz6qDH01Hw",
    "duration": "PT1H45M58S"
  },
  {
    "id": "ifyxY2r4pg4",
    "title": "No Way Out - மர்மம் நிறைந்த Thriller திரைப்படம்🔥| Super Hit Cinema | Thanthi One | 29th July",
    "description": "A debt-ridden man, who invests a large sum of money before the COVID-19 pandemic, attempts to commit an unthinkable act only to get embroiled in further trouble.\n \nStarring : Ramesh Pisharody, Dharmajan Bolgatty, Basil Joseph, Raveena N\nDOP : Vargheese David\nEditor : KR Midhun\nMusic Director : KR Rahul\nBackground Score: Christy Joby \nMusic production team : Vaishakh Jyothis, Christy Joby\nSound Design: Rajesh PM\nSound Mixing: Gijumon T Bruce\nChief Associate Director : Akash Ramkumar \nArt Director: Girish Menon\nCostumer : Sujith Mattannur \nMakeup : Amal Chandran\nColourist : Vivek Nair\nAction Cheoregrapghy : Mafia Sasi\nChoreography : Shanthi Master\nDon't forget to SUBSCRIBE Thanthi One YouTube Channel👉\nFollow us on Social Media for Latest Updates :\nFacebook : \nInstagram : \nX (Twitter)  : \nMinmini     :  \nWhatsapp Channel :  \nShareChat : \n   Bolgatty",
    "thumbnails": {
      "default": {
        "url": "https://i.ytimg.com/vi/ifyxY2r4pg4/default.jpg",
        "width": 120,
        "height": 90
      },
      "medium": {
        "url": "https://i.ytimg.com/vi/ifyxY2r4pg4/mqdefault.jpg",
        "width": 320,
        "height": 180
      },
      "high": {
        "url": "https://i.ytimg.com/vi/ifyxY2r4pg4/hqdefault.jpg",
        "width": 480,
        "height": 360
      },
      "standard": {
        "url": "https://i.ytimg.com/vi/ifyxY2r4pg4/sddefault.jpg",
        "width": 640,
        "height": 480
      },
      "maxres": {
        "url": "https://i.ytimg.com/vi/ifyxY2r4pg4/maxresdefault.jpg",
        "width": 1280,
        "height": 720
      }
    },
    "playlistId": "PLkdhKIzS8nUlgYeQhV3UY4ibQ0nAGuK1y",
    "publishedAt": "2025-09-17T10:09:49Z",
    "channelTitle": "Thanthi One",
    "videoOwnerChannelTitle": "Thanthi One",
    "videoOwnerChannelId": "UCFYqIFxANnSDsnz6qDH01Hw",
    "duration": "PT1H31M42S"
  },
  {
    "id": "21wLtGMmTgQ",
    "title": "Universal Soldiers 3 - மர்மம் நிறைந்த Action திரைப்படம்💥| Super Hit Cinema | Thanthi One | 25th July",
    "description": "Former UniSol Luc Deveraux is thrust into a high-stakes mission to save the planet from NGU, a deadly android engineered by terrorists. The situation intensifies as he faces off against his old nemesis, Andrew Scott, in a battle that will determine the fate of humanity.\nClick To Watch Super Hit Cinemas : \nDon't forget to SUBSCRIBE Thanthi One YouTube Channel👉\nFollow us on Social Media for Latest Updates :\nFacebook : \nInstagram : \nX (Twitter)  : \nMinmini     :  \nWhatsapp Channel :  \nShareChat : \nTelegram :",
    "thumbnails": {
      "default": {
        "url": "https://i.ytimg.com/vi/21wLtGMmTgQ/default.jpg",
        "width": 120,
        "height": 90
      },
      "medium": {
        "url": "https://i.ytimg.com/vi/21wLtGMmTgQ/mqdefault.jpg",
        "width": 320,
        "height": 180
      },
      "high": {
        "url": "https://i.ytimg.com/vi/21wLtGMmTgQ/hqdefault.jpg",
        "width": 480,
        "height": 360
      },
      "standard": {
        "url": "https://i.ytimg.com/vi/21wLtGMmTgQ/sddefault.jpg",
        "width": 640,
        "height": 480
      },
      "maxres": {
        "url": "https://i.ytimg.com/vi/21wLtGMmTgQ/maxresdefault.jpg",
        "width": 1280,
        "height": 720
      }
    },
    "playlistId": "PLkdhKIzS8nUlgYeQhV3UY4ibQ0nAGuK1y",
    "publishedAt": "2025-09-17T10:09:49Z",
    "channelTitle": "Thanthi One",
    "videoOwnerChannelTitle": "Thanthi One",
    "videoOwnerChannelId": "UCFYqIFxANnSDsnz6qDH01Hw",
    "duration": "PT1H33M40S"
  },
  {
    "id": "Qiqn6a3-jeM",
    "title": "Adventures of Mahaan - மர்மம் நிறைந்த கலகலப்பான Thriller திரைப்படம்🔥| Super Hit Cinema | Thanthi One",
    "description": "Adventures of Mahaan tracks a shy marketing executive's journey after a memory-wiping accident, encountering quirky characters. Pallavi, a determined private detective, aids him in unraveling mysteries and finding his true self amidst the whimsical chaos.\nDon't forget to SUBSCRIBE Thanthi One YouTube Channel👉\nFollow us on Social Media for Latest Updates :\nFacebook : \nInstagram : \nX (Twitter)  : \nMinmini     :  \nWhatsapp Channel :  \nShareChat :",
    "thumbnails": {
      "default": {
        "url": "https://i.ytimg.com/vi/Qiqn6a3-jeM/default.jpg",
        "width": 120,
        "height": 90
      },
      "medium": {
        "url": "https://i.ytimg.com/vi/Qiqn6a3-jeM/mqdefault.jpg",
        "width": 320,
        "height": 180
      },
      "high": {
        "url": "https://i.ytimg.com/vi/Qiqn6a3-jeM/hqdefault.jpg",
        "width": 480,
        "height": 360
      },
      "standard": {
        "url": "https://i.ytimg.com/vi/Qiqn6a3-jeM/sddefault.jpg",
        "width": 640,
        "height": 480
      },
      "maxres": {
        "url": "https://i.ytimg.com/vi/Qiqn6a3-jeM/maxresdefault.jpg",
        "width": 1280,
        "height": 720
      }
    },
    "playlistId": "PLkdhKIzS8nUlgYeQhV3UY4ibQ0nAGuK1y",
    "publishedAt": "2025-09-17T10:09:49Z",
    "channelTitle": "Thanthi One",
    "videoOwnerChannelTitle": "Thanthi One",
    "videoOwnerChannelId": "UCFYqIFxANnSDsnz6qDH01Hw",
    "duration": "PT2H42M20S"
  }
]